synaps/__init__.py
synaps/cli/__init__.py
synaps/cli/__main__.py
synaps/cli/client.py
synaps/cli/sen0311.py
synaps/cli/sen0395.py
synaps/common/__init__.py
synaps/common/paths.py
synaps/common/relay.py
synaps/common/sen0311.py
synaps/common/sen0395.py
synaps/common/socket.py
synaps/common/switch.py
synaps/service/__init__.py
synaps/service/__main__.py
synaps/service/api.py
synaps/service/cfg.py
synaps/service/err.py
synaps/service/ksm.py
synaps/service/log.py
synaps/service/mqtt.py
synaps/service/rpio.py
synaps/service/sen0311.py
synaps/service/sen0395.py
synaps/service/ws.py
synaps-0.5.0.dist-info/entry_points.txt
synaps-0.5.0.dist-info/licenses/LICENSE
synaps-0.5.0.dist-info/WHEEL
synaps-0.5.0.dist-info/METADATA
synaps-0.5.0.dist-info/RECORD
