Metadata-Version: 2.4
Name: synaps
Version: 0.5.0
Summary: This distribution package consists of two main components:
Author-email: Stan Svec <dev@stansvec.com>
Requires-Python: >=3.11.2
Classifier: License :: OSI Approved :: MIT License
License-File: LICENSE
Requires-Dist: sensation>=0.2.1
Requires-Dist: gpiozero>=2.0.1
Requires-Dist: pigpio>=1.78
Requires-Dist: click>=8.1.7
Requires-Dist: rich-click>=1.7.3
Requires-Dist: aiofiles>=24.1.0
Requires-Dist: tomli>=2.0.1
Requires-Dist: gmqtt>=0.6.16 
Requires-Dist: websockets>=12.0
Project-URL: Home, https://github.com/symbol-signal/synaps
